virtualmod.py
virtualmod-1.0.0.dist-info/METADATA
virtualmod-1.0.0.dist-info/RECORD
virtualmod-1.0.0.dist-info/WHEEL
virtualmod-1.0.0.dist-info/top_level.txt
