Metadata-Version: 2.1
Name: virtualmod
Version: 1.0.0
Summary: Python package for creating and importing virtual modules.
Home-page: https://github.com/brettlangdon/virtualmod
Author: Brett Langdon
Author-email: me@brett.is
License: MIT
Platform: any
Classifier: Development Status :: 5 - Production/Stable
Classifier: Intended Audience :: Developers
Classifier: License :: OSI Approved :: MIT License
Classifier: Operating System :: OS Independent
Classifier: Programming Language :: Python :: 3
Classifier: Programming Language :: Python
